userpref/admin.py
userpref/__init__.py
userpref/views.py
userpref/models.py
userpref/urls.py
userpref/migrations/__init__.py
django_userpref-0.1.0a5.dist-info/DESCRIPTION.rst
django_userpref-0.1.0a5.dist-info/top_level.txt
django_userpref-0.1.0a5.dist-info/METADATA
django_userpref-0.1.0a5.dist-info/metadata.json
django_userpref-0.1.0a5.dist-info/RECORD
django_userpref-0.1.0a5.dist-info/WHEEL
