Metadata-Version: 2.0
Name: django-userpref
Version: 0.1.0a5
Summary: Django user preferences
Home-page: https://github.com/soerenbe/django-userpref
Author: The Python Packaging Authority
Author-email: soeren.berger@u1337.de
License: GPL-v3
Keywords: django user preferences
Platform: UNKNOWN
Classifier: Development Status :: 3 - Alpha
Classifier: Intended Audience :: Developers
Classifier: Framework :: Django
Classifier: License :: OSI Approved :: GNU General Public License v3 (GPLv3)
Classifier: Programming Language :: Python :: 2.7
Classifier: Programming Language :: Python :: 3
Requires-Dist: django
